CMakeLists.txt
LICENSE
MANIFEST.in
README.md
cppkin.sh
setup.py
cmake/FindBenchMark.cmake
cmake/FindBoost_Pack.cmake
cmake/FindBottle.cmake
cmake/FindCURL.cmake
cmake/FindCore.cmake
cmake/FindPyBind.cmake
cmake/FindPython.cmake
cmake/FindRapidJson.cmake
cmake/FindSpdLog.cmake
cmake/FindSweetPy.cmake
cmake/FindThrift.cmake
cmake/InstallBenchMark.cmake
cmake/InstallBoost_Pack.cmake
cmake/InstallBottle.cmake
cmake/InstallCURL.cmake
cmake/InstallCore.cmake
cmake/InstallPyBind.cmake
cmake/InstallRapidJson.cmake
cmake/InstallSpdLog.cmake
cmake/InstallSweetPy.cmake
cmake/InstallThrift.cmake
cmake/cppkinMacro.cmake
cmake/installThirdParty.cmake
cppkin/__init__.py
cppkin/cppkin.py
cppkin.egg-info/PKG-INFO
cppkin.egg-info/SOURCES.txt
cppkin.egg-info/dependency_links.txt
cppkin.egg-info/top_level.txt
src/Annotation.cpp
src/Annotation.h
src/AnnotationType.cpp
src/AnnotationType.h
src/BinaryAnnotation.cpp
src/BinaryAnnotation.h
src/ConfigParams.cpp
src/ConfigParams.h
src/ConfigTags.cpp
src/ConfigTags.h
src/Encoder.cpp
src/Encoder.h
src/EncodingContext.cpp
src/EncodingContext.h
src/EncodingTypes.cpp
src/EncodingTypes.h
src/Export.h
src/HttpTransport.cpp
src/HttpTransport.h
src/JsonEncoder.h
src/Sampler.cpp
src/Sampler.h
src/ScribeTransport.cpp
src/ScribeTransport.h
src/SimpleAnnotation.cpp
src/SimpleAnnotation.h
src/Span.cpp
src/Span.h
src/SpanContainer.cpp
src/SpanContainer.h
src/StubTransport.h
src/ThriftEncoder.h
src/Trace.cpp
src/Trace.h
src/Transport.cpp
src/Transport.h
src/TransportFactory.cpp
src/TransportFactory.h
src/TransportManager.cpp
src/TransportManager.h
src/TransportType.cpp
src/TransportType.h
src/cppkin.cpp
src/cppkin.h
src/cppkinWrapper.cpp
src/span_impl.cpp
src/span_impl.h